sight_machine/__init__.py
sight_machine/binary_loggable.py
sight_machine/binary_logger.py
sight_machine/binary_logger_bis.py
sight_machine/in_action.py
sight_machine/tests/__init__.py
sight_machine/tests/test_binary_logger.py
sight_machine/tests/test_binary_logger_bis.py
sight_machine-0.5.dist-info/LICENSE
sight_machine-0.5.dist-info/METADATA
sight_machine-0.5.dist-info/WHEEL
sight_machine-0.5.dist-info/top_level.txt
sight_machine-0.5.dist-info/RECORD
