Metadata-Version: 2.1
Name: sight-machine
Version: 0.5
Summary: Simple binary logger
Home-page: http://github.com/dbajet/sight_machine/
Author: Denis Bajet
Author-email: dbajet@gmail.com
License: UNKNOWN
Platform: UNKNOWN
Requires-Python: >=3.7
